mahapala/__init__.py
mahapala/fruits_classification.py
mahapala/mahapala.py
MahaPala-2023.12.16.dist-info/METADATA
MahaPala-2023.12.16.dist-info/WHEEL
MahaPala-2023.12.16.dist-info/top_level.txt
MahaPala-2023.12.16.dist-info/RECORD
