Metadata-Version: 2.1
Name: MahaPala
Version: 2023.12.16
Summary: Detection of fruits disease by using Machine learning
Home-page: https://github.com/AbhimanyuHK/MahaPala
Author: Abhimanyu HK
Author-email: manyu1994@hotmail.com
Requires-Dist: tensorflow ==2.15.0
Requires-Dist: matplotlib
Requires-Dist: numpy
Requires-Dist: opencv-python
